LICENSE
bodhiext/qdrant/__init__.py
bodhiext/qdrant/_qdrant.py
bodhiext/qdrant/_version.py
bodhiext_qdrant-0.1.2.dist-info/LICENSE
bodhiext_qdrant-0.1.2.dist-info/METADATA
bodhiext_qdrant-0.1.2.dist-info/WHEEL
bodhiext_qdrant-0.1.2.dist-info/entry_points.txt
bodhiext_qdrant-0.1.2.dist-info/RECORD
